LICENSE
MANIFEST.in
README.rst
setup.py
docs/Makefile
docs/source/conf.py
docs/source/example.py
docs/source/index.rst
sphinx_readable_theme/__init__.py
sphinx_readable_theme/__init__.pyc
sphinx_readable_theme.egg-info/PKG-INFO
sphinx_readable_theme.egg-info/SOURCES.txt
sphinx_readable_theme.egg-info/dependency_links.txt
sphinx_readable_theme.egg-info/not-zip-safe
sphinx_readable_theme.egg-info/top_level.txt
sphinx_readable_theme/readable/layout.html
sphinx_readable_theme/readable/relations.html
sphinx_readable_theme/readable/theme.conf
sphinx_readable_theme/readable/static/pygments.css
sphinx_readable_theme/readable/static/readable.css_t