Metadata-Version: 1.1
Name: sphinx-readable-theme
Version: 0.1.0
Summary: Sphinx Readable Theme
Home-page: https://github.com/ignacysokolowski/sphinx-readable-theme
Author: Ignacy Sokolowski
Author-email: ignacy.sokolowski@gmail.com
License: Copyright (c) 2013 Ignacy Sokołowski
